prompt/__init__.py
prompt/ingestion/__init__.py
prompt/ingestion/cli.py
prompt/ingestion/import_data.py
prompt/ingestion/init_cache.py
prompt/ingestion/init_schema.py
prompt/ingestion/init_suggestion.py
prompt/ingestion/preprocess.py
prompt/ingestion/util.py
prompt/retrieval/__init__.py
prompt/retrieval/advanced_engine.py
prompt/retrieval/graphql_doc_search.py
prompt/retrieval/interface.py
prompt/retrieval/simple_engine.py
server/__init__.py
server/api.py
server/cli.py
server/frontend/out/asset-manifest.json
server/frontend/out/favicon.ico
server/frontend/out/index.html
server/frontend/out/logo192.png
server/frontend/out/logo512.png
server/frontend/out/manifest.json
server/frontend/out/robots.txt
server/frontend/out/static/css/main.a3f20bbf.css
server/frontend/out/static/css/main.a3f20bbf.css.map
server/frontend/out/static/css/main.aaa0e22a.css
server/frontend/out/static/css/main.aaa0e22a.css.map
server/frontend/out/static/css/main.bd5a5873.css
server/frontend/out/static/css/main.bd5a5873.css.map
server/frontend/out/static/css/main.bf0b3339.css
server/frontend/out/static/css/main.bf0b3339.css.map
server/frontend/out/static/css/main.fa6f4d43.css
server/frontend/out/static/css/main.fa6f4d43.css.map
server/frontend/out/static/js/787.cda612ba.chunk.js
server/frontend/out/static/js/787.cda612ba.chunk.js.map
server/frontend/out/static/js/main.01f5b92e.js
server/frontend/out/static/js/main.01f5b92e.js.LICENSE.txt
server/frontend/out/static/js/main.01f5b92e.js.map
server/frontend/out/static/js/main.54c68eae.js
server/frontend/out/static/js/main.54c68eae.js.LICENSE.txt
server/frontend/out/static/js/main.54c68eae.js.map
server/frontend/out/static/js/main.5d67fbf9.js
server/frontend/out/static/js/main.5d67fbf9.js.LICENSE.txt
server/frontend/out/static/js/main.5d67fbf9.js.map
server/frontend/out/static/js/main.7177c7b4.js
server/frontend/out/static/js/main.7177c7b4.js.LICENSE.txt
server/frontend/out/static/js/main.7177c7b4.js.map
server/frontend/out/static/js/main.9bc9dfcc.js
tenxbot-0.0.1.dist-info/METADATA
tenxbot-0.0.1.dist-info/WHEEL
tenxbot-0.0.1.dist-info/entry_points.txt
tenxbot-0.0.1.dist-info/top_level.txt
tenxbot-0.0.1.dist-info/RECORD
