Metadata-Version: 2.1
Name: tenxbot
Version: 0.0.1
Summary: Welcome to Nana: The RAGtriever tenx chatbot
Home-page: https://github.com/10xac/tenx-chatbot
Author: tenx
Author-email: team@10academy.org
Classifier: License :: OSI Approved :: BSD License
Classifier: Programming Language :: Python :: 3
Classifier: Programming Language :: Python :: 3.6
Classifier: Programming Language :: Python :: 3.7
Classifier: Programming Language :: Python :: 3.8
Classifier: Programming Language :: Python :: 3.9
Classifier: Programming Language :: Python :: 3.10
Requires-Dist: weaviate-client >=3.23.1
Requires-Dist: python-dotenv >=1.0.0
Requires-Dist: openai >=0.27.9
Requires-Dist: wasabi >=1.1.2
Requires-Dist: spacy
Requires-Dist: fastapi >=0.102.0
Requires-Dist: uvicorn[standard]
Requires-Dist: click >=8.1.7
Provides-Extra: dev
Requires-Dist: pytest ; extra == 'dev'
Requires-Dist: wheel ; extra == 'dev'
Requires-Dist: twine ; extra == 'dev'
Requires-Dist: black ; extra == 'dev'
Requires-Dist: setuptools ; extra == 'dev'
